Metadata-Version: 2.1
Name: tabular-camel
Version: 2024.11.12
Summary: A DataFrame-focused Solution for Tabular Dataset
Home-page: https://github.com/SilenceX12138/Camel
Author: Xiangjian Jiang
Author-email: silencejiang12138@gmail.com
License: Apache Software License
Classifier: License :: OSI Approved :: Apache Software License
Classifier: Programming Language :: Python :: 3
Classifier: Programming Language :: Python :: 3.10
Requires-Python: >=3.10.0
License-File: LICENSE
